ipyvisus/__init__.py
ipyvisus/__version__.py
ipyvisus/server.py
ipyvisus/viewer2d.py
ipyvisus/viewer3d.py
ipyvisus-0.2.0.dist-info/LICENSE
ipyvisus-0.2.0.dist-info/METADATA
ipyvisus-0.2.0.dist-info/WHEEL
ipyvisus-0.2.0.dist-info/top_level.txt
ipyvisus-0.2.0.dist-info/RECORD
